[
    "20.02.2024 19:46:13",
    {
        "10c": [
            [
                3,
                "Eng",
                "OG57",
                "Jas",
                false
            ]
        ],
        "10d": [
            [
                3,
                "Rus",
                "OG58",
                "Lv",
                false
            ]
        ],
        "5c": [
            [
                5,
                "Mat",
                "OG11",
                "Hf",
                false
            ]
        ],
        "5d": [
            [
                1,
                "Mat",
                "OG22",
                "Be",
                false
            ]
        ],
        "5e": [
            [
                6,
                "Eng",
                "OG21",
                "Hu",
                false
            ]
        ],
        "6a": [
            [
                1,
                "Chor",
                "Aula",
                "Ho",
                true
            ],
            [
                5,
                "Mus",
                "OG31",
                "May",
                false
            ],
            [
                6,
                "Mus",
                "Mus2",
                "---",
                false
            ]
        ],
        "6b": [
            [
                1,
                "Chor",
                "Mus1",
                "Ho",
                true
            ]
        ],
        "6c": [
            [
                1,
                "Chor",
                "Mus1",
                "Ho",
                true
            ],
            [
                3,
                "Ges",
                "OG33",
                "Be",
                false
            ],
            [
                4,
                "Ges",
                "OG33",
                "Ka",
                false
            ]
        ],
        "6d": [
            [
                1,
                "Chor",
                "Mus1",
                "Ho",
                true
            ]
        ],
        "6g": [
            [
                1,
                "Chor",
                "Mus1",
                "Ho",
                true
            ]
        ],
        "8a": [
            [
                1,
                "",
                "OG51",
                "Whs",
                false
            ],
            [
                2,
                "",
                "OG51",
                "Whs",
                false
            ],
            [
                3,
                "",
                "OG51",
                "Ki",
                false
            ],
            [
                4,
                "",
                "OG51",
                "Ki",
                false
            ],
            [
                5,
                "",
                "OG51",
                "Eck",
                false
            ],
            [
                6,
                "",
                "OG51",
                "Eck",
                false
            ],
            [
                1,
                "Che",
                "Che1",
                "Whs",
                true
            ],
            [
                2,
                "Che",
                "Che1",
                "Whs",
                true
            ],
            [
                3,
                "Lat",
                "OG51",
                "Ki",
                true
            ],
            [
                4,
                "Lat",
                "OG51",
                "Ki",
                true
            ]
        ],
        "8b": [
            [
                1,
                "",
                "OG52",
                "Fre",
                false
            ],
            [
                2,
                "",
                "OG52",
                "L\u00fc",
                false
            ],
            [
                3,
                "",
                "OG52",
                "Gb",
                false
            ],
            [
                4,
                "",
                "OG52",
                "Bey",
                false
            ],
            [
                5,
                "",
                "OG52",
                "Ge",
                false
            ],
            [
                6,
                "",
                "OG52",
                "Ge",
                false
            ],
            [
                1,
                "Mat",
                "OG52",
                "Fre",
                true
            ],
            [
                2,
                "Eng",
                "OG52",
                "Bas",
                true
            ],
            [
                3,
                "Che",
                "Che1",
                "Zim",
                true
            ],
            [
                4,
                "Che",
                "Che1",
                "Zim",
                true
            ],
            [
                5,
                "Gri",
                "OG52",
                "Ge",
                true
            ],
            [
                6,
                "Gri",
                "OG52",
                "Ge",
                true
            ]
        ],
        "8c": [
            [
                1,
                "",
                "OG53",
                "Pi",
                false
            ],
            [
                2,
                "",
                "OG53",
                "Pi",
                false
            ],
            [
                3,
                "",
                "OG53",
                "Kw",
                false
            ],
            [
                4,
                "",
                "OG53",
                "Kw",
                false
            ],
            [
                5,
                "",
                "OG53",
                "Pg",
                false
            ],
            [
                6,
                "",
                "OG53",
                "Pg",
                false
            ],
            [
                1,
                "Gri",
                "OG53",
                "Pi",
                true
            ],
            [
                2,
                "Lat",
                "OG53",
                "Pi",
                true
            ],
            [
                3,
                "Mus",
                "Mus2",
                "Kw",
                true
            ],
            [
                4,
                "Mus",
                "Mus2",
                "Kw",
                true
            ],
            [
                5,
                "Mat",
                "OG53",
                "Pg",
                true
            ],
            [
                6,
                "Mat",
                "OG53",
                "Pg",
                true
            ]
        ],
        "8d": [
            [
                1,
                "",
                "OG37",
                "Ort",
                false
            ],
            [
                2,
                "",
                "OG37",
                "Ort",
                false
            ],
            [
                3,
                "",
                "OG37",
                "Kna",
                false
            ],
            [
                4,
                "",
                "OG37",
                "Wr",
                false
            ],
            [
                6,
                "",
                "OG37",
                "Wr",
                false
            ],
            [
                1,
                "Sp",
                "Sp3",
                "Ort",
                true
            ],
            [
                2,
                "Sp",
                "Sp3",
                "Ort",
                true
            ],
            [
                3,
                "Eng",
                "OG37",
                "Kna",
                true
            ],
            [
                4,
                "KStd",
                "OG37",
                "Wr",
                true
            ],
            [
                5,
                "Lat",
                "OG37",
                "Wr",
                true
            ],
            [
                6,
                "Rus",
                "OG37",
                "Wr",
                true
            ]
        ],
        "8e": [
            [
                1,
                "",
                "OG43",
                "Zh",
                false
            ],
            [
                2,
                "",
                "OG43",
                "Zh",
                false
            ],
            [
                3,
                "",
                "OG43",
                "Sk",
                false
            ],
            [
                4,
                "",
                "OG43",
                "Fre",
                false
            ],
            [
                5,
                "",
                "OG43",
                "Ki",
                false
            ],
            [
                6,
                "",
                "OG43",
                "Gr",
                false
            ],
            [
                1,
                "Eng",
                "OG43",
                "Zh",
                true
            ],
            [
                2,
                "Eng",
                "OG43",
                "Zh",
                true
            ],
            [
                3,
                "Lat",
                "OG43",
                "Sk",
                true
            ],
            [
                4,
                "Mat",
                "OG43",
                "Fre",
                true
            ],
            [
                5,
                "Che",
                "Che1",
                "Zim",
                true
            ],
            [
                6,
                "Che",
                "Che1",
                "Zim",
                true
            ]
        ],
        "8f": [
            [
                1,
                "",
                "OG36",
                "Ms",
                false
            ],
            [
                2,
                "",
                "OG36",
                "Ms",
                false
            ],
            [
                3,
                "",
                "OG36",
                "Pts",
                false
            ],
            [
                4,
                "",
                "OG36",
                "Pts",
                false
            ],
            [
                5,
                "",
                "OG36",
                "Sch\u00f6",
                false
            ],
            [
                6,
                "",
                "OG36",
                "Sch\u00f6",
                false
            ],
            [
                1,
                "Mat",
                "OG36",
                "Ms",
                true
            ],
            [
                2,
                "Mat",
                "OG36",
                "Ms",
                true
            ],
            [
                3,
                "Deu",
                "OG36",
                "Pts",
                true
            ],
            [
                4,
                "Deu",
                "OG36",
                "Pts",
                true
            ],
            [
                5,
                "Rus",
                "OG36",
                "Sch\u00f6",
                true
            ],
            [
                6,
                "Rus",
                "OG36",
                "Sch\u00f6",
                true
            ]
        ],
        "9b": [
            [
                1,
                "Phy",
                "OG42",
                "Hei",
                false
            ],
            [
                2,
                "Phy",
                "OG42",
                "Pk",
                false
            ],
            [
                5,
                "Mat",
                "OG42",
                "Re",
                false
            ],
            [
                5,
                "Mat",
                "OG42",
                "Re",
                false
            ],
            [
                6,
                "Mat",
                "OG42",
                "Re",
                false
            ],
            [
                6,
                "",
                "OG42",
                "Re",
                false
            ]
        ]
    }
]